nanb/__init__.py
nanb/cell.py
nanb/client.py
nanb/config.py
nanb/help_screen.py
nanb/main.py
nanb/nanb.css
nanb/parser.py
nanb/server.py
nanb/server_manager.py
nanb/widgets.py
nanb/tests/test_client.py
nanb-0.1.1.dist-info/LICENSE
nanb-0.1.1.dist-info/METADATA
nanb-0.1.1.dist-info/WHEEL
nanb-0.1.1.dist-info/entry_points.txt
nanb-0.1.1.dist-info/top_level.txt
nanb-0.1.1.dist-info/RECORD
