Metadata-Version: 2.1
Name: nanb
Version: 0.1.1
Summary: Not A NoteBook
Author-email: Espen Notodden <espen@enotodden.com>
Project-URL: Homepage, https://github.com/enotodden/nanb
Project-URL: Bug Tracker, https://github.com/enotodden/nanb/issues
Classifier: Programming Language :: Python :: 3
Classifier: License :: OSI Approved :: MIT License
Classifier: Operating System :: OS Independent
Requires-Python: >=3.9
License-File: LICENSE
Requires-Dist: aiohttp ==3.8.5
Requires-Dist: aiosignal ==1.3.1
Requires-Dist: anyio ==4.0.0
Requires-Dist: async-timeout ==4.0.3
Requires-Dist: attrs ==23.1.0
Requires-Dist: charset-normalizer ==3.3.0
Requires-Dist: click ==8.1.7
Requires-Dist: frozenlist ==1.4.0
Requires-Dist: idna ==3.4
Requires-Dist: importlib-metadata ==6.8.0
Requires-Dist: linkify-it-py ==2.0.2
Requires-Dist: markdown-it-py ==3.0.0
Requires-Dist: mdit-py-plugins ==0.4.0
Requires-Dist: mdurl ==0.1.2
Requires-Dist: msgpack ==1.0.7
Requires-Dist: multidict ==6.0.4
Requires-Dist: Pygments ==2.16.1
Requires-Dist: rich ==13.5.3
Requires-Dist: sniffio ==1.3.0
Requires-Dist: textual ==0.38.1
Requires-Dist: textual-dev ==1.2.1
Requires-Dist: toml ==0.10.2
Requires-Dist: tree-sitter ==0.20.2
Requires-Dist: tree-sitter-languages ==1.7.0
Requires-Dist: typing-extensions ==4.8.0
Requires-Dist: uc-micro-py ==1.0.2
Requires-Dist: watchfiles ==0.20.0
Requires-Dist: yarl ==1.9.2
Requires-Dist: zipp ==3.17.0
